flask_authorization_panda
