Metadata-Version: 1.1
Name: Flask-Authorization-Panda
Version: 0.1.1
Summary: Flask Authorization for Pandas!
Home-page: https://github.com/eikonomega/flask-authorization-panda
Author: Mike Dunn
Author-email: mike@eikonomega.com
License: MIT
Platform: UNKNOWN
Classifier: Intended Audience :: Developers
Classifier: License :: OSI Approved :: MIT License
Classifier: Operating System :: OS Independent
Classifier: Programming Language :: Python
Classifier: Topic :: Software Development :: Libraries :: Python Modules
